newcode_utils/__init__.py
newcode_utils/apps.py
newcode_utils/admins/__init__.py
newcode_utils/admins/audit_admin.py
newcode_utils/helpers/__init__.py
newcode_utils/helpers/utils.py
newcode_utils/helpers/utils_permission_rest.py
newcode_utils/migrations/__init__.py
newcode_utils/migrations/__pycache__/__init__.cpython-37.pyc
newcode_utils/models/__init__.py
newcode_utils/models/audit.py
newcode_utils/models/__pycache__/__init__.cpython-37.pyc
newcode_utils/models/__pycache__/audit.cpython-37.pyc
newcode_utils-0.1.2.dist-info/LICENSE
newcode_utils-0.1.2.dist-info/METADATA
newcode_utils-0.1.2.dist-info/WHEEL
newcode_utils-0.1.2.dist-info/top_level.txt
newcode_utils-0.1.2.dist-info/RECORD
