Metadata-Version: 2.1
Name: newcode-utils
Version: 0.1.2
Summary: Necessary elements for the development of apps.
Home-page: https://github.com/New-Code-S-A-S/newcode_utils
Author: Camilo Suarez
Author-email: juancamilosuarezquinones@gmail.com
Maintainer: NewCode_
Maintainer-email: new.code.2523@gmail.com
Keywords: utils,newcode-utils,NewCode,Audit
Classifier: Environment :: Web Environment
Classifier: Framework :: Django
Classifier: License :: OSI Approved :: MIT License
Classifier: Operating System :: OS Independent
Classifier: Programming Language :: Python :: 3
Classifier: Programming Language :: Python :: 3 :: Only
Classifier: Programming Language :: Python :: 3.8
Classifier: Topic :: Software Development :: Libraries :: Python Modules
License-File: LICENSE
Requires-Dist: markdown (>=3.2.2)
Requires-Dist: MarkupPy (>=1.14)
Requires-Dist: MarkupSafe (>=1.1.1)
Requires-Dist: djangorestframework (>=3.11.2)
Requires-Dist: django-filter (>=2.2.0)
Requires-Dist: django-rest-swagger (>=2.2.0)
Requires-Dist: django (>=3.0)
Requires-Dist: django-crum (>=0.7.5)
Requires-Dist: celery (>=4.4.2)
Requires-Dist: django-import-export (>=2.1.0)
Requires-Dist: slackclient (>=2.9.3)
